clidpy/__main__.py
clidpy-1.0.dist-info/LICENSE
clidpy-1.0.dist-info/METADATA
clidpy-1.0.dist-info/WHEEL
clidpy-1.0.dist-info/top_level.txt
clidpy-1.0.dist-info/RECORD
